ai_reqs-0.1.1.dist-info/licenses/LICENCE
ai_reqs_generator/main.py
ai_reqs_generator/standard_libraries.py
ai_reqs-0.1.1.dist-info/METADATA
ai_reqs-0.1.1.dist-info/WHEEL
ai_reqs-0.1.1.dist-info/entry_points.txt
ai_reqs-0.1.1.dist-info/top_level.txt
ai_reqs-0.1.1.dist-info/RECORD
