Metadata-Version: 2.4
Name: ai-reqs
Version: 0.1.1
Summary: Generate requirements.txt for Python projects, using an AI to resolve complex and ambiguous dependencies.
Author-email: Thomas Manjooran <thomasmanjooran20@gmail.com>
License-Expression: MIT
Project-URL: Homepage, https://github.com/thomasmanjooran/ai-reqs
Project-URL: Bug Tracker, https://github.com/thomasmanjooran/ai-reqs/issues
Classifier: Programming Language :: Python :: 3
Classifier: Operating System :: OS Independent
Classifier: Topic :: Software Development
Classifier: Topic :: Terminals
Requires-Python: >=3.8
License-File: LICENCE
Dynamic: license-file
